autoregressor/__init__.py
autoregressor/autoregressor.py
autoregressor/compute.py
autoregressor-1.0.0.dist-info/LICENSE
autoregressor-1.0.0.dist-info/METADATA
autoregressor-1.0.0.dist-info/WHEEL
autoregressor-1.0.0.dist-info/top_level.txt
autoregressor-1.0.0.dist-info/RECORD
