Metadata-Version: 2.1
Name: autoregressor
Version: 1.0.0
Summary: Automated entire process of building and training regression based models
Home-page: https://github.com/jaydulera/autoregressor
Author: Jay Dulera
Author-email: jaydulera01@gmail.com
License: MIT
Platform: UNKNOWN
Classifier: License :: OSI Approved :: MIT License
Classifier: Programming Language :: Python :: 3
Classifier: Programming Language :: Python :: 3.7
Classifier: Intended Audience :: Developers
Classifier: Topic :: Scientific/Engineering :: Artificial Intelligence
Requires-Dist: sklearn
Requires-Dist: pandas
Requires-Dist: numpy
